wagtail_bucketav/__init__.py
wagtail_bucketav/apps.py
wagtail_bucketav/test_example.py
wagtail_bucketav-0.0.1.dist-info/LICENSE
wagtail_bucketav-0.0.1.dist-info/WHEEL
wagtail_bucketav-0.0.1.dist-info/METADATA
wagtail_bucketav-0.0.1.dist-info/RECORD
